ti_containers/__init__.py
ti_containers/config.py
ti_containers/constant.py
ti_containers/exception.py
ti_containers/executer.py
ti_containers/train.py
ti_containers/utils.py
ti_containers/mxnet/__init__.py
ti_containers/mxnet/prepare.py
ti_containers/pytorch/__init__.py
ti_containers/pytorch/prepare.py
ti_containers/sklearn/__init__.py
ti_containers/sklearn/prepare.py
ti_containers/tensorflow/__init__.py
ti_containers/tensorflow/prepare.py
ti_containers-1.2.22.dist-info/LICENSE
ti_containers-1.2.22.dist-info/METADATA
ti_containers-1.2.22.dist-info/WHEEL
ti_containers-1.2.22.dist-info/entry_points.txt
ti_containers-1.2.22.dist-info/top_level.txt
ti_containers-1.2.22.dist-info/RECORD
