Metadata-Version: 2.1
Name: ti-containers
Version: 1.2.22
Summary: Open source library for training container on TencentCloud TIONE.
Home-page: https://cloud.tencent.com
Author: TencentCloud TIONE
License: Apache License 2.0
Keywords: TencentCloud ML TI AI Training
Platform: UNKNOWN
Requires-Dist: retrying (==1.3.3)
Requires-Dist: six (==1.12.0)
